listcompare/__init__.py
listcompare/listcompare.py
listcompare/setup.py
listcompare/test_listcompare.py
listcompare-1.1.10.dist-info/DESCRIPTION.rst
listcompare-1.1.10.dist-info/METADATA
listcompare-1.1.10.dist-info/RECORD
listcompare-1.1.10.dist-info/WHEEL
listcompare-1.1.10.dist-info/metadata.json
listcompare-1.1.10.dist-info/top_level.txt
